one_msg_waba_sdk/__init__.py
one_msg_waba_sdk/api_client.py
one_msg_waba_sdk/api_response.py
one_msg_waba_sdk/configuration.py
one_msg_waba_sdk/exceptions.py
one_msg_waba_sdk/py.typed
one_msg_waba_sdk/rest.py
one_msg_waba_sdk/api/__init__.py
one_msg_waba_sdk/api/channel_api.py
one_msg_waba_sdk/api/media_api.py
one_msg_waba_sdk/api/messaging_api.py
one_msg_waba_sdk/api/products_catalogs_api.py
one_msg_waba_sdk/api/templates_api.py
one_msg_waba_sdk/api/webhooks_api.py
one_msg_waba_sdk/models/__init__.py
one_msg_waba_sdk/models/ack.py
one_msg_waba_sdk/models/add_template_request.py
one_msg_waba_sdk/models/channel_extended_statistics.py
one_msg_waba_sdk/models/channel_extended_statistics_inner.py
one_msg_waba_sdk/models/channel_statistics.py
one_msg_waba_sdk/models/channel_status.py
one_msg_waba_sdk/models/chat_id_prop.py
one_msg_waba_sdk/models/commerce.py
one_msg_waba_sdk/models/commerce_params.py
one_msg_waba_sdk/models/contacts.py
one_msg_waba_sdk/models/contacts_contacts_inner.py
one_msg_waba_sdk/models/contacts_request.py
one_msg_waba_sdk/models/get_ack_info.py
one_msg_waba_sdk/models/get_ack_info_hooks_inner.py
one_msg_waba_sdk/models/get_commerce.py
one_msg_waba_sdk/models/get_commerce_inner.py
one_msg_waba_sdk/models/get_ip.py
one_msg_waba_sdk/models/get_me.py
one_msg_waba_sdk/models/get_me401_response.py
one_msg_waba_sdk/models/get_messages.py
one_msg_waba_sdk/models/get_messages_messages_inner.py
one_msg_waba_sdk/models/get_templates.py
one_msg_waba_sdk/models/get_templates_templates_inner.py
one_msg_waba_sdk/models/me_components.py
one_msg_waba_sdk/models/media_id.py
one_msg_waba_sdk/models/message.py
one_msg_waba_sdk/models/message_id_prop.py
one_msg_waba_sdk/models/phone_prop.py
one_msg_waba_sdk/models/read_message_request.py
one_msg_waba_sdk/models/remove_template_request.py
one_msg_waba_sdk/models/send_contact_request.py
one_msg_waba_sdk/models/send_file_request.py
one_msg_waba_sdk/models/send_list_request.py
one_msg_waba_sdk-1.3.0.dist-info/METADATA
one_msg_waba_sdk-1.3.0.dist-info/WHEEL
one_msg_waba_sdk-1.3.0.dist-info/top_level.txt
one_msg_waba_sdk-1.3.0.dist-info/RECORD
