Metadata-Version: 2.1
Name: one-msg-waba-sdk
Version: 1.3.0
Summary: one_msg_waba_sdk
Home-page: 
Author: OpenAPI Generator community
Author-email: hello@1msg.io
Keywords: OpenAPI,OpenAPI-Generator,one_msg_waba_sdk
Requires-Dist: urllib3 <2.1.0,>=1.25.3
Requires-Dist: python-dateutil
Requires-Dist: pydantic <2,>=1.10.5
Requires-Dist: aenum
